mma_fighters_sdk/__init__.py
mma_fighters_sdk/battle.py
mma_fighters_sdk/card.py
mma_fighters_sdk/card_param.py
mma_fighters_sdk/const.py
mma_fighters_sdk/utils.py
mma_fighters_sdk-1.3.0.dist-info/LICENSE.txt
mma_fighters_sdk-1.3.0.dist-info/METADATA
mma_fighters_sdk-1.3.0.dist-info/WHEEL
mma_fighters_sdk-1.3.0.dist-info/top_level.txt
mma_fighters_sdk-1.3.0.dist-info/RECORD
