Metadata-Version: 2.1
Name: mma-fighters-sdk
Version: 1.3.0
Summary: SDK for mma_fighters_sdk
Home-page: https://github.com/hallrizon-io/mma_fighters_game_sdk
Author: Kostiantyn Minkov
Author-email: hallrizon.usa@gmail.com
License: BSD 2-clause
Classifier: Programming Language :: Python :: 3
Classifier: License :: OSI Approved :: MIT License
Classifier: Operating System :: OS Independent
Requires-Python: >=3.6
License-File: LICENSE.txt
